{
  "updatedAt": "2026-05-14T19:43:33.622Z",
  "quotes": {
    "LAES": {
      "c": 3.0901,
      "d": 0.13010001,
      "dp": 4.3880067,
      "o": 2.9,
      "h": 3.13,
      "l": 2.83,
      "pc": 2.96,
      "currency": "USD",
      "name": "SEALSQ Corp",
      "exchange": "NasdaqGS",
      "fiftyTwoWeekHigh": 8.71,
      "fiftyTwoWeekLow": 1.99,
      "volume": 9554946,
      "averageVolume": 10054273,
      "marketCap": 688393920,
      "peTTM": null,
      "eps": -0.24,
      "divYield": 0,
      "marketState": "REGULAR",
      "extendedLabel": null
    },
    "COHX": {
      "c": 66.38,
      "d": -0.84000397,
      "dp": -1.2496339,
      "o": 66.99,
      "h": 69.48,
      "l": 62.53,
      "pc": 67.22,
      "currency": "USD",
      "name": "Tradr 2X Long COHR Daily ETF",
      "exchange": "Cboe US",
      "fiftyTwoWeekHigh": 69.8,
      "fiftyTwoWeekLow": 20.64,
      "volume": 1003423,
      "averageVolume": 647806,
      "marketCap": null,
      "peTTM": null,
      "eps": null,
      "divYield": 0,
      "marketState": "REGULAR",
      "extendedLabel": null
    },
    "BABA": {
      "c": 141.06,
      "d": -4.75,
      "dp": -3.2576642,
      "o": 140.98,
      "h": 143.98,
      "l": 138.64,
      "pc": 145.81,
      "currency": "USD",
      "name": "Alibaba Group Holding Limited",
      "exchange": "NYSE",
      "fiftyTwoWeekHigh": 192.67,
      "fiftyTwoWeekLow": 103.71,
      "volume": 16755909,
      "averageVolume": 10945360,
      "marketCap": 338410045440,
      "peTTM": 24.74737,
      "eps": 5.7,
      "divYield": 0,
      "marketState": "REGULAR",
      "extendedLabel": null
    },
    "6488.TWO": {
      "c": 788,
      "d": 38,
      "dp": 5.0666666,
      "o": 785,
      "h": 805,
      "l": 780,
      "pc": 750,
      "currency": "TWD",
      "name": "GLOBALWAFERS CO LTD",
      "exchange": "Taipei Exchange",
      "fiftyTwoWeekHigh": 849,
      "fiftyTwoWeekLow": 278.5,
      "volume": 2721794,
      "averageVolume": 6645246,
      "marketCap": 376753618944,
      "peTTM": 49.25,
      "eps": 16,
      "divYield": 0,
      "marketState": "PREPRE",
      "extendedLabel": null
    },
    "6634.TWO": {
      "c": 76.1,
      "d": -3.800003,
      "dp": -4.7559485,
      "o": 80,
      "h": 85,
      "l": 72.4,
      "pc": 79.9,
      "currency": "TWD",
      "name": "SINEW",
      "exchange": "Taipei Exchange",
      "fiftyTwoWeekHigh": 85,
      "fiftyTwoWeekLow": 29.05,
      "volume": 915233,
      "averageVolume": 152777,
      "marketCap": 5425087488,
      "peTTM": null,
      "eps": -1.66,
      "divYield": 0,
      "marketState": "PREPRE",
      "extendedLabel": null
    },
    "1560.TW": {
      "c": 650,
      "d": 17,
      "dp": 2.685624,
      "o": 640,
      "h": 657,
      "l": 627,
      "pc": 633,
      "currency": "TWD",
      "name": "KINIK CO",
      "exchange": "Taiwan",
      "fiftyTwoWeekHigh": 683,
      "fiftyTwoWeekLow": 266,
      "volume": 3540318,
      "averageVolume": 2895815,
      "marketCap": 95739797504,
      "peTTM": 69.44445,
      "eps": 9.36,
      "divYield": 0,
      "marketState": "PREPRE",
      "extendedLabel": null
    },
    "3105.TWO": {
      "c": 483.5,
      "d": -12,
      "dp": -2.421796,
      "o": 503,
      "h": 504,
      "l": 482,
      "pc": 495.5,
      "currency": "TWD",
      "name": "WIN SEMICONDUCTORS CORP",
      "exchange": "Taipei Exchange",
      "fiftyTwoWeekHigh": 637,
      "fiftyTwoWeekLow": 79.4,
      "volume": 20731037,
      "averageVolume": 31460363,
      "marketCap": 204975177728,
      "peTTM": 120.57356,
      "eps": 4.01,
      "divYield": 0.004036327,
      "marketState": "PREPRE",
      "extendedLabel": null
    },
    "6451.TW": {
      "c": 525,
      "d": 47,
      "dp": 9.832636,
      "o": 484,
      "h": 525,
      "l": 471.5,
      "pc": 478,
      "currency": "TWD",
      "name": "SHUNSIN TECHNOLOGY HOLDINGS LTD",
      "exchange": "Taiwan",
      "fiftyTwoWeekHigh": 556,
      "fiftyTwoWeekLow": 120,
      "volume": 10564748,
      "averageVolume": 4401157,
      "marketCap": 55741243392,
      "peTTM": 2019.2308,
      "eps": 0.26,
      "divYield": 0,
      "marketState": "PREPRE",
      "extendedLabel": null
    },
    "SIVE.ST": {
      "c": 56.65,
      "d": 13.510002,
      "dp": 31.31665,
      "o": 45.9,
      "h": 56.65,
      "l": 45,
      "pc": 43.14,
      "currency": "SEK",
      "name": "Sivers Semiconductors AB",
      "exchange": "Stockholm",
      "fiftyTwoWeekHigh": 59.1,
      "fiftyTwoWeekLow": 2.85,
      "volume": 14363199,
      "averageVolume": 23082206,
      "marketCap": 16798694400,
      "peTTM": null,
      "eps": -0.69,
      "divYield": 0,
      "marketState": "CLOSED",
      "extendedLabel": null
    },
    "IQE.L": {
      "c": 49.6,
      "d": -0.9000015,
      "dp": -1.7821813,
      "o": 50.4,
      "h": 51.1454,
      "l": 47.55,
      "pc": 50.5,
      "currency": "GBp",
      "name": "IQE PLC ORD 1P",
      "exchange": "LSE",
      "fiftyTwoWeekHigh": 72.9,
      "fiftyTwoWeekLow": 4.655,
      "volume": 20083225,
      "averageVolume": 34988286,
      "marketCap": 486021600,
      "peTTM": null,
      "eps": -0.05,
      "divYield": 0,
      "marketState": "POSTPOST",
      "extendedLabel": null
    },
    "VITL": {
      "c": 8.51,
      "d": 0.1800003,
      "dp": 2.160868,
      "o": 8.33,
      "h": 8.62,
      "l": 8.155,
      "pc": 8.33,
      "currency": "USD",
      "name": "Vital Farms, Inc.",
      "exchange": "NasdaqGM",
      "fiftyTwoWeekHigh": 53.125,
      "fiftyTwoWeekLow": 7.95,
      "volume": 2324905,
      "averageVolume": 3266439,
      "marketCap": 364640384,
      "peTTM": 8.182693,
      "eps": 1.04,
      "divYield": 0,
      "marketState": "REGULAR",
      "extendedLabel": null
    },
    "ADBE": {
      "c": 236.94,
      "d": 0.8699951,
      "dp": 0.3685327,
      "o": 237,
      "h": 238.24,
      "l": 231.74,
      "pc": 236.07,
      "currency": "USD",
      "name": "Adobe Inc.",
      "exchange": "NasdaqGS",
      "fiftyTwoWeekHigh": 422.95,
      "fiftyTwoWeekLow": 224.13,
      "volume": 3814293,
      "averageVolume": 5564027,
      "marketCap": 95771148288,
      "peTTM": 13.807693,
      "eps": 17.16,
      "divYield": 0,
      "marketState": "REGULAR",
      "extendedLabel": null
    },
    "NVO": {
      "c": 45.805,
      "d": -1.2750015,
      "dp": -2.7081594,
      "o": 46.79,
      "h": 46.84,
      "l": 45.5401,
      "pc": 47.08,
      "currency": "USD",
      "name": "Novo Nordisk A/S",
      "exchange": "NYSE",
      "fiftyTwoWeekHigh": 81.44,
      "fiftyTwoWeekLow": 35.12,
      "volume": 10577653,
      "averageVolume": 20347181,
      "marketCap": 203046731776,
      "peTTM": 10.603009,
      "eps": 4.32,
      "divYield": 0.24851316,
      "marketState": "REGULAR",
      "extendedLabel": null
    },
    "PFE": {
      "c": 25.725,
      "d": -0.2349987,
      "dp": -0.90523386,
      "o": 26.07,
      "h": 26.1,
      "l": 25.72,
      "pc": 25.96,
      "currency": "USD",
      "name": "Pfizer, Inc.",
      "exchange": "NYSE",
      "fiftyTwoWeekHigh": 28.75,
      "fiftyTwoWeekLow": 22.09,
      "volume": 17453455,
      "averageVolume": 37956519,
      "marketCap": 146618204160,
      "peTTM": 19.637405,
      "eps": 1.31,
      "divYield": 0.06625578,
      "marketState": "REGULAR",
      "extendedLabel": null
    },
    "OXY": {
      "c": 56.905,
      "d": 0.7249985,
      "dp": 1.290492,
      "o": 56,
      "h": 57.2705,
      "l": 55.845,
      "pc": 56.18,
      "currency": "USD",
      "name": "Occidental Petroleum Corporatio",
      "exchange": "NYSE",
      "fiftyTwoWeekHigh": 67.45,
      "fiftyTwoWeekLow": 38.8,
      "volume": 6539777,
      "averageVolume": 17280965,
      "marketCap": 56599687168,
      "peTTM": 76.89864,
      "eps": 0.74,
      "divYield": 0.01744393,
      "marketState": "REGULAR",
      "extendedLabel": null
    },
    "LWLG": {
      "c": 14.935,
      "d": -3.2799997,
      "dp": -18.007135,
      "o": 17.025,
      "h": 17.025,
      "l": 14.2801,
      "pc": 18.215,
      "currency": "USD",
      "name": "Lightwave Logic, Inc.",
      "exchange": "NasdaqCM",
      "fiftyTwoWeekHigh": 18.71,
      "fiftyTwoWeekLow": 0.92,
      "volume": 15866810,
      "averageVolume": 7241839,
      "marketCap": 2249370880,
      "peTTM": null,
      "eps": -0.16,
      "divYield": 0,
      "marketState": "REGULAR",
      "extendedLabel": null
    },
    "TPRO.MI": {
      "c": 19.71,
      "d": 0.7199993,
      "dp": 3.7914655,
      "o": 19.16,
      "h": 19.71,
      "l": 18.63,
      "pc": 18.99,
      "currency": "EUR",
      "name": "TECHNOPROBE",
      "exchange": "Milan",
      "fiftyTwoWeekHigh": 20.36,
      "fiftyTwoWeekLow": 5.92,
      "volume": 435374,
      "averageVolume": 616399,
      "marketCap": 12620693504,
      "peTTM": 131.4,
      "eps": 0.15,
      "divYield": 0,
      "marketState": "POSTPOST",
      "extendedLabel": null
    },
    "USAR": {
      "c": 25.1501,
      "d": -0.26989937,
      "dp": -1.06176,
      "o": 25.78,
      "h": 26.12,
      "l": 23.35,
      "pc": 25.42,
      "currency": "USD",
      "name": "USA Rare Earth, Inc.",
      "exchange": "NasdaqGM",
      "fiftyTwoWeekHigh": 43.98,
      "fiftyTwoWeekLow": 8,
      "volume": 16414668,
      "averageVolume": 15325898,
      "marketCap": 5482359808,
      "peTTM": null,
      "eps": -3.31,
      "divYield": 0,
      "marketState": "REGULAR",
      "extendedLabel": null
    },
    "SMHN.DE": {
      "c": 93.9,
      "d": 6.1500015,
      "dp": 7.0085487,
      "o": 89.75,
      "h": 94,
      "l": 88.2,
      "pc": 87.75,
      "currency": "EUR",
      "name": "SUSS MicroTec SE              N",
      "exchange": "XETRA",
      "fiftyTwoWeekHigh": 94,
      "fiftyTwoWeekLow": 24,
      "volume": 133207,
      "averageVolume": 138861,
      "marketCap": 1794948992,
      "peTTM": 31.83051,
      "eps": 2.95,
      "divYield": 0.0034188034,
      "marketState": "POSTPOST",
      "extendedLabel": null
    },
    "INTC": {
      "c": 116.01,
      "d": -4.279999,
      "dp": -3.5580668,
      "o": 114.645,
      "h": 118.5699,
      "l": 113.17,
      "pc": 120.29,
      "currency": "USD",
      "name": "Intel Corporation",
      "exchange": "NasdaqGS",
      "fiftyTwoWeekHigh": 132.75,
      "fiftyTwoWeekLow": 18.97,
      "volume": 100800703,
      "averageVolume": 112903740,
      "marketCap": 583066255360,
      "peTTM": null,
      "eps": -0.6,
      "divYield": 0,
      "marketState": "REGULAR",
      "extendedLabel": null
    },
    "TSLA": {
      "c": 443.59,
      "d": -1.6799927,
      "dp": -0.37729752,
      "o": 446.425,
      "h": 451.97,
      "l": 441.16,
      "pc": 445.27,
      "currency": "USD",
      "name": "Tesla, Inc.",
      "exchange": "NasdaqGS",
      "fiftyTwoWeekHigh": 498.83,
      "fiftyTwoWeekLow": 273.21,
      "volume": 41016626,
      "averageVolume": 62928765,
      "marketCap": 1666001534976,
      "peTTM": 414.57007,
      "eps": 1.07,
      "divYield": 0,
      "marketState": "REGULAR",
      "extendedLabel": null
    },
    "GOOG": {
      "c": 396.935,
      "d": -2.105011,
      "dp": -0.5275188,
      "o": 393.93,
      "h": 399.104,
      "l": 392.728,
      "pc": 399.04,
      "currency": "USD",
      "name": "Alphabet Inc.",
      "exchange": "NasdaqGS",
      "fiftyTwoWeekHigh": 399.93,
      "fiftyTwoWeekLow": 163.33,
      "volume": 10712264,
      "averageVolume": 19422800,
      "marketCap": 4809043738624,
      "peTTM": 30.23115,
      "eps": 13.13,
      "divYield": 0.0021050521,
      "marketState": "REGULAR",
      "extendedLabel": null
    },
    "000333.SZ": {
      "c": 81.81,
      "d": 1.4300003,
      "dp": 1.77905,
      "o": 79.65,
      "h": 82.08,
      "l": 80.39,
      "pc": 80.38,
      "currency": "CNY",
      "name": "MIDEA GROUP CO LTD",
      "exchange": "Shenzhen",
      "fiftyTwoWeekHigh": 83.17,
      "fiftyTwoWeekLow": 69.88,
      "volume": 38926688,
      "averageVolume": 27413630,
      "marketCap": 622431633408,
      "peTTM": 14.0567,
      "eps": 5.82,
      "divYield": 0.0534959,
      "marketState": "PREPRE",
      "extendedLabel": null
    },
    "300782.SZ": {
      "c": 140.88,
      "d": 13.950005,
      "dp": 10.990314,
      "o": 104.5,
      "h": 144.9,
      "l": 129.47,
      "pc": 126.93,
      "currency": "CNY",
      "name": "MAXSCEND MICROELECTRONICS COMPA",
      "exchange": "Shenzhen",
      "fiftyTwoWeekHigh": 144.9,
      "fiftyTwoWeekLow": 66.9,
      "volume": 64114333,
      "averageVolume": 22852198,
      "marketCap": 81004175360,
      "peTTM": null,
      "eps": -0.82,
      "divYield": 0,
      "marketState": "PREPRE",
      "extendedLabel": null
    }
  },
  "profiles": {
    "LAES": {
      "name": "SEALSQ Corp",
      "logo": "https://static2.finnhub.io/file/publicdatany/finnhubimage/stock_logo/LAES.png",
      "sector": null,
      "industry": null,
      "country": null,
      "exchange": "NasdaqGS",
      "weburl": null,
      "currency": "USD",
      "marketCap": 688393920,
      "ipo": null,
      "ticker": null
    },
    "COHX": {
      "name": "Tradr 2X Long COHR Daily ETF",
      "logo": "https://static2.finnhub.io/file/publicdatany/finnhubimage/stock_logo/COHX.png",
      "sector": null,
      "industry": null,
      "country": null,
      "exchange": "Cboe US",
      "weburl": null,
      "currency": "USD",
      "marketCap": null,
      "ipo": null,
      "ticker": null
    },
    "BABA": {
      "name": "Alibaba Group Holding Limited",
      "logo": "https://static2.finnhub.io/file/publicdatany/finnhubimage/stock_logo/BABA.png",
      "sector": null,
      "industry": null,
      "country": null,
      "exchange": "NYSE",
      "weburl": null,
      "currency": "USD",
      "marketCap": 338410045440,
      "ipo": null,
      "ticker": null
    },
    "6488.TWO": {
      "name": "GLOBALWAFERS CO LTD",
      "logo": null,
      "sector": null,
      "industry": null,
      "country": null,
      "exchange": "Taipei Exchange",
      "weburl": null,
      "currency": "TWD",
      "marketCap": 376753618944,
      "ipo": null,
      "ticker": null
    },
    "6634.TWO": {
      "name": "SINEW",
      "logo": null,
      "sector": null,
      "industry": null,
      "country": null,
      "exchange": "Taipei Exchange",
      "weburl": null,
      "currency": "TWD",
      "marketCap": 5425087488,
      "ipo": null,
      "ticker": null
    },
    "1560.TW": {
      "name": "KINIK CO",
      "logo": null,
      "sector": null,
      "industry": null,
      "country": null,
      "exchange": "Taiwan",
      "weburl": null,
      "currency": "TWD",
      "marketCap": 95739797504,
      "ipo": null,
      "ticker": null
    },
    "3105.TWO": {
      "name": "WIN SEMICONDUCTORS CORP",
      "logo": null,
      "sector": null,
      "industry": null,
      "country": null,
      "exchange": "Taipei Exchange",
      "weburl": null,
      "currency": "TWD",
      "marketCap": 204975177728,
      "ipo": null,
      "ticker": null
    },
    "6451.TW": {
      "name": "SHUNSIN TECHNOLOGY HOLDINGS LTD",
      "logo": null,
      "sector": null,
      "industry": null,
      "country": null,
      "exchange": "Taiwan",
      "weburl": null,
      "currency": "TWD",
      "marketCap": 55741243392,
      "ipo": null,
      "ticker": null
    },
    "SIVE.ST": {
      "name": "Sivers Semiconductors AB",
      "logo": null,
      "sector": null,
      "industry": null,
      "country": null,
      "exchange": "Stockholm",
      "weburl": null,
      "currency": "SEK",
      "marketCap": 16798694400,
      "ipo": null,
      "ticker": null
    },
    "IQE.L": {
      "name": "IQE PLC ORD 1P",
      "logo": null,
      "sector": null,
      "industry": null,
      "country": null,
      "exchange": "LSE",
      "weburl": null,
      "currency": "GBp",
      "marketCap": 486021600,
      "ipo": null,
      "ticker": null
    },
    "VITL": {
      "name": "Vital Farms, Inc.",
      "logo": "https://static2.finnhub.io/file/publicdatany/finnhubimage/stock_logo/VITL.png",
      "sector": null,
      "industry": null,
      "country": null,
      "exchange": "NasdaqGM",
      "weburl": null,
      "currency": "USD",
      "marketCap": 364640384,
      "ipo": null,
      "ticker": null
    },
    "ADBE": {
      "name": "Adobe Inc.",
      "logo": "https://static2.finnhub.io/file/publicdatany/finnhubimage/stock_logo/ADBE.png",
      "sector": null,
      "industry": null,
      "country": null,
      "exchange": "NasdaqGS",
      "weburl": null,
      "currency": "USD",
      "marketCap": 95771148288,
      "ipo": null,
      "ticker": null
    },
    "NVO": {
      "name": "Novo Nordisk A/S",
      "logo": "https://static2.finnhub.io/file/publicdatany/finnhubimage/stock_logo/NVO.png",
      "sector": null,
      "industry": null,
      "country": null,
      "exchange": "NYSE",
      "weburl": null,
      "currency": "USD",
      "marketCap": 203046731776,
      "ipo": null,
      "ticker": null
    },
    "PFE": {
      "name": "Pfizer, Inc.",
      "logo": "https://static2.finnhub.io/file/publicdatany/finnhubimage/stock_logo/PFE.png",
      "sector": null,
      "industry": null,
      "country": null,
      "exchange": "NYSE",
      "weburl": null,
      "currency": "USD",
      "marketCap": 146618204160,
      "ipo": null,
      "ticker": null
    },
    "OXY": {
      "name": "Occidental Petroleum Corporatio",
      "logo": "https://static2.finnhub.io/file/publicdatany/finnhubimage/stock_logo/OXY.png",
      "sector": null,
      "industry": null,
      "country": null,
      "exchange": "NYSE",
      "weburl": null,
      "currency": "USD",
      "marketCap": 56599687168,
      "ipo": null,
      "ticker": null
    },
    "LWLG": {
      "name": "Lightwave Logic, Inc.",
      "logo": "https://static2.finnhub.io/file/publicdatany/finnhubimage/stock_logo/LWLG.png",
      "sector": null,
      "industry": null,
      "country": null,
      "exchange": "NasdaqCM",
      "weburl": null,
      "currency": "USD",
      "marketCap": 2249370880,
      "ipo": null,
      "ticker": null
    },
    "TPRO.MI": {
      "name": "TECHNOPROBE",
      "logo": null,
      "sector": null,
      "industry": null,
      "country": null,
      "exchange": "Milan",
      "weburl": null,
      "currency": "EUR",
      "marketCap": 12620693504,
      "ipo": null,
      "ticker": null
    },
    "USAR": {
      "name": "USA Rare Earth, Inc.",
      "logo": "https://static2.finnhub.io/file/publicdatany/finnhubimage/stock_logo/USAR.png",
      "sector": null,
      "industry": null,
      "country": null,
      "exchange": "NasdaqGM",
      "weburl": null,
      "currency": "USD",
      "marketCap": 5482359808,
      "ipo": null,
      "ticker": null
    },
    "SMHN.DE": {
      "name": "SUSS MicroTec SE              N",
      "logo": null,
      "sector": null,
      "industry": null,
      "country": null,
      "exchange": "XETRA",
      "weburl": null,
      "currency": "EUR",
      "marketCap": 1794948992,
      "ipo": null,
      "ticker": null
    },
    "INTC": {
      "name": "Intel Corporation",
      "logo": "https://static2.finnhub.io/file/publicdatany/finnhubimage/stock_logo/INTC.png",
      "sector": null,
      "industry": null,
      "country": null,
      "exchange": "NasdaqGS",
      "weburl": null,
      "currency": "USD",
      "marketCap": 583066255360,
      "ipo": null,
      "ticker": null
    },
    "TSLA": {
      "name": "Tesla, Inc.",
      "logo": "https://static2.finnhub.io/file/publicdatany/finnhubimage/stock_logo/TSLA.png",
      "sector": null,
      "industry": null,
      "country": null,
      "exchange": "NasdaqGS",
      "weburl": null,
      "currency": "USD",
      "marketCap": 1666001534976,
      "ipo": null,
      "ticker": null
    },
    "GOOG": {
      "name": "Alphabet Inc.",
      "logo": "https://static2.finnhub.io/file/publicdatany/finnhubimage/stock_logo/GOOG.png",
      "sector": null,
      "industry": null,
      "country": null,
      "exchange": "NasdaqGS",
      "weburl": null,
      "currency": "USD",
      "marketCap": 4809043738624,
      "ipo": null,
      "ticker": null
    },
    "000333.SZ": {
      "name": "MIDEA GROUP CO LTD",
      "logo": null,
      "sector": null,
      "industry": null,
      "country": null,
      "exchange": "Shenzhen",
      "weburl": null,
      "currency": "CNY",
      "marketCap": 622431633408,
      "ipo": null,
      "ticker": null
    },
    "300782.SZ": {
      "name": "MAXSCEND MICROELECTRONICS COMPA",
      "logo": null,
      "sector": null,
      "industry": null,
      "country": null,
      "exchange": "Shenzhen",
      "weburl": null,
      "currency": "CNY",
      "marketCap": 81004175360,
      "ipo": null,
      "ticker": null
    }
  },
  "metrics": {
    "LAES": {
      "peTTM": null,
      "pbAnnual": null,
      "fiftyTwoWeekHigh": 8.71,
      "fiftyTwoWeekLow": 1.99,
      "divYield": 0,
      "beta": null,
      "eps": -0.24,
      "volume": 9554946,
      "averageVolume": 10054273
    },
    "COHX": {
      "peTTM": null,
      "pbAnnual": null,
      "fiftyTwoWeekHigh": 69.8,
      "fiftyTwoWeekLow": 20.64,
      "divYield": 0,
      "beta": null,
      "eps": null,
      "volume": 1003423,
      "averageVolume": 647806
    },
    "BABA": {
      "peTTM": 24.74737,
      "pbAnnual": null,
      "fiftyTwoWeekHigh": 192.67,
      "fiftyTwoWeekLow": 103.71,
      "divYield": 0,
      "beta": null,
      "eps": 5.7,
      "volume": 16755909,
      "averageVolume": 10945360
    },
    "6488.TWO": {
      "peTTM": 49.25,
      "pbAnnual": null,
      "fiftyTwoWeekHigh": 849,
      "fiftyTwoWeekLow": 278.5,
      "divYield": 0,
      "beta": null,
      "eps": 16,
      "volume": 2721794,
      "averageVolume": 6645246
    },
    "6634.TWO": {
      "peTTM": null,
      "pbAnnual": null,
      "fiftyTwoWeekHigh": 85,
      "fiftyTwoWeekLow": 29.05,
      "divYield": 0,
      "beta": null,
      "eps": -1.66,
      "volume": 915233,
      "averageVolume": 152777
    },
    "1560.TW": {
      "peTTM": 69.44445,
      "pbAnnual": null,
      "fiftyTwoWeekHigh": 683,
      "fiftyTwoWeekLow": 266,
      "divYield": 0,
      "beta": null,
      "eps": 9.36,
      "volume": 3540318,
      "averageVolume": 2895815
    },
    "3105.TWO": {
      "peTTM": 120.57356,
      "pbAnnual": null,
      "fiftyTwoWeekHigh": 637,
      "fiftyTwoWeekLow": 79.4,
      "divYield": 0.4036327,
      "beta": null,
      "eps": 4.01,
      "volume": 20731037,
      "averageVolume": 31460363
    },
    "6451.TW": {
      "peTTM": 2019.2308,
      "pbAnnual": null,
      "fiftyTwoWeekHigh": 556,
      "fiftyTwoWeekLow": 120,
      "divYield": 0,
      "beta": null,
      "eps": 0.26,
      "volume": 10564748,
      "averageVolume": 4401157
    },
    "SIVE.ST": {
      "peTTM": null,
      "pbAnnual": null,
      "fiftyTwoWeekHigh": 59.1,
      "fiftyTwoWeekLow": 2.85,
      "divYield": 0,
      "beta": null,
      "eps": -0.69,
      "volume": 14363199,
      "averageVolume": 23082206
    },
    "IQE.L": {
      "peTTM": null,
      "pbAnnual": null,
      "fiftyTwoWeekHigh": 72.9,
      "fiftyTwoWeekLow": 4.655,
      "divYield": 0,
      "beta": null,
      "eps": -0.05,
      "volume": 20083225,
      "averageVolume": 34988286
    },
    "VITL": {
      "peTTM": 8.182693,
      "pbAnnual": null,
      "fiftyTwoWeekHigh": 53.125,
      "fiftyTwoWeekLow": 7.95,
      "divYield": 0,
      "beta": null,
      "eps": 1.04,
      "volume": 2324905,
      "averageVolume": 3266439
    },
    "ADBE": {
      "peTTM": 13.807693,
      "pbAnnual": null,
      "fiftyTwoWeekHigh": 422.95,
      "fiftyTwoWeekLow": 224.13,
      "divYield": 0,
      "beta": null,
      "eps": 17.16,
      "volume": 3814293,
      "averageVolume": 5564027
    },
    "NVO": {
      "peTTM": 10.603009,
      "pbAnnual": null,
      "fiftyTwoWeekHigh": 81.44,
      "fiftyTwoWeekLow": 35.12,
      "divYield": 24.851316,
      "beta": null,
      "eps": 4.32,
      "volume": 10577653,
      "averageVolume": 20347181
    },
    "PFE": {
      "peTTM": 19.637405,
      "pbAnnual": null,
      "fiftyTwoWeekHigh": 28.75,
      "fiftyTwoWeekLow": 22.09,
      "divYield": 6.625578,
      "beta": null,
      "eps": 1.31,
      "volume": 17453455,
      "averageVolume": 37956519
    },
    "OXY": {
      "peTTM": 76.89864,
      "pbAnnual": null,
      "fiftyTwoWeekHigh": 67.45,
      "fiftyTwoWeekLow": 38.8,
      "divYield": 1.744393,
      "beta": null,
      "eps": 0.74,
      "volume": 6539777,
      "averageVolume": 17280965
    },
    "LWLG": {
      "peTTM": null,
      "pbAnnual": null,
      "fiftyTwoWeekHigh": 18.71,
      "fiftyTwoWeekLow": 0.92,
      "divYield": 0,
      "beta": null,
      "eps": -0.16,
      "volume": 15866810,
      "averageVolume": 7241839
    },
    "TPRO.MI": {
      "peTTM": 131.4,
      "pbAnnual": null,
      "fiftyTwoWeekHigh": 20.36,
      "fiftyTwoWeekLow": 5.92,
      "divYield": 0,
      "beta": null,
      "eps": 0.15,
      "volume": 435374,
      "averageVolume": 616399
    },
    "USAR": {
      "peTTM": null,
      "pbAnnual": null,
      "fiftyTwoWeekHigh": 43.98,
      "fiftyTwoWeekLow": 8,
      "divYield": 0,
      "beta": null,
      "eps": -3.31,
      "volume": 16414668,
      "averageVolume": 15325898
    },
    "SMHN.DE": {
      "peTTM": 31.83051,
      "pbAnnual": null,
      "fiftyTwoWeekHigh": 94,
      "fiftyTwoWeekLow": 24,
      "divYield": 0.34188034,
      "beta": null,
      "eps": 2.95,
      "volume": 133207,
      "averageVolume": 138861
    },
    "INTC": {
      "peTTM": null,
      "pbAnnual": null,
      "fiftyTwoWeekHigh": 132.75,
      "fiftyTwoWeekLow": 18.97,
      "divYield": 0,
      "beta": null,
      "eps": -0.6,
      "volume": 100800703,
      "averageVolume": 112903740
    },
    "TSLA": {
      "peTTM": 414.57007,
      "pbAnnual": null,
      "fiftyTwoWeekHigh": 498.83,
      "fiftyTwoWeekLow": 273.21,
      "divYield": 0,
      "beta": null,
      "eps": 1.07,
      "volume": 41016626,
      "averageVolume": 62928765
    },
    "GOOG": {
      "peTTM": 30.23115,
      "pbAnnual": null,
      "fiftyTwoWeekHigh": 399.93,
      "fiftyTwoWeekLow": 163.33,
      "divYield": 0.21050521,
      "beta": null,
      "eps": 13.13,
      "volume": 10712264,
      "averageVolume": 19422800
    },
    "000333.SZ": {
      "peTTM": 14.0567,
      "pbAnnual": null,
      "fiftyTwoWeekHigh": 83.17,
      "fiftyTwoWeekLow": 69.88,
      "divYield": 5.34959,
      "beta": null,
      "eps": 5.82,
      "volume": 38926688,
      "averageVolume": 27413630
    },
    "300782.SZ": {
      "peTTM": null,
      "pbAnnual": null,
      "fiftyTwoWeekHigh": 144.9,
      "fiftyTwoWeekLow": 66.9,
      "divYield": 0,
      "beta": null,
      "eps": -0.82,
      "volume": 64114333,
      "averageVolume": 22852198
    }
  },
  "fxRates": {
    "USD": 1,
    "TWD": 0.031721864,
    "SEK": 0.10689642,
    "GBp": 0.013397642000000001,
    "EUR": 1.1674061,
    "CNY": 0.14739263
  }
}
